roastedbyai/__init__.py
roastedbyai/errors.py
roastedbyai/models.py
roastedbyai/roasted.py
roastedbyai-1.3.0.dist-info/LICENSE
roastedbyai-1.3.0.dist-info/LICENSE.html
roastedbyai-1.3.0.dist-info/LICENSE.md
roastedbyai-1.3.0.dist-info/METADATA
roastedbyai-1.3.0.dist-info/WHEEL
roastedbyai-1.3.0.dist-info/top_level.txt
roastedbyai-1.3.0.dist-info/RECORD
