Metadata-Version: 2.1
Name: roastedbyai
Version: 1.3.0
Summary: A package to roast and get roasted by AI.
Home-page: https://github.com/jvherck/roastedbyai
Author: jvherck
Author-email: jan@vhjan.me
Maintainer: jvherck
Maintainer-email: jan@vhjan.me
License: CC BY-NC-SA 4.0
Project-URL: Documentation, https://github.com/jvherck/roastedbyai
Project-URL: Source, https://github.com/jvherck/roastedbyai
Project-URL: Tracker, https://github.com/jvherck/roastedbyai/issues
Keywords: python,ai,roasting,roasted,roast,roastedbyai
Classifier: Development Status :: 4 - Beta
Classifier: Intended Audience :: Developers
Classifier: Intended Audience :: Other Audience
Classifier: Natural Language :: English
Classifier: Programming Language :: Python :: 3
Classifier: Programming Language :: Python :: 3 :: Only
Classifier: Programming Language :: Python :: 3.7
Classifier: Programming Language :: Python :: 3.8
Classifier: Programming Language :: Python :: 3.9
Classifier: Programming Language :: Python :: 3.10
Classifier: Programming Language :: Python :: 3.11
Classifier: Programming Language :: Python :: 3.12
Classifier: Operating System :: Unix
Classifier: Operating System :: MacOS
Classifier: Operating System :: Microsoft :: Windows
Classifier: License :: Free for non-commercial use
Classifier: Topic :: Games/Entertainment
Classifier: Topic :: Other/Nonlisted Topic
Classifier: Topic :: Scientific/Engineering :: Artificial Intelligence
Classifier: Topic :: Software Development :: Libraries :: Python Modules
Requires-Python: >=3.7
License-File: LICENSE
License-File: LICENSE.html
License-File: LICENSE.md
